{
  "company_name": "MKEY Technology",
  "company_slug": "mkey-technology",
  "description": "Image processing based and artificial intelligence supported automation systems",
  "website": "https://www.mkeytechnology.com",
  "location": "Konya, Turkey, Asia",
  "vertical": "Image process",
  "funding_amount": 0,
  "funding_stage": null,
  "uses_genai": true,
  "build_patterns": [],
  "confidence_score": null,
  "tech_stack": [],
  "models_mentioned": [],
  "vertical_taxonomy": {
    "ontology_id": "startup-vertical-taxonomy",
    "ontology_version": "2026-02-07_v1",
    "primary": {
      "vertical_id": "industrial_manufacturing",
      "vertical_label": "Industrial & Manufacturing",
      "sub_vertical_id": "robotics_automation",
      "sub_vertical_label": "Robotics & Automation",
      "leaf_id": "robotics_automation",
      "leaf_label": "Robotics & Automation"
    },
    "path": [
      {
        "id": "industrial_manufacturing",
        "label": "Industrial & Manufacturing",
        "confidence": 0.85
      },
      {
        "id": "robotics_automation",
        "label": "Robotics & Automation",
        "confidence": 0.85
      }
    ]
  },
  "sub_vertical": "Robotics & Automation"
}
