{
  "company_name": "Polygraf AI",
  "company_slug": "polygraf-ai",
  "description": "Advanced AI-native solutions to combat AI-driven fraud, data leaks, and compliance risks",
  "website": "https://polygraf.ai",
  "location": "Austin, USA, Asia",
  "vertical": "Artificial intelligence",
  "funding_amount": 9500000.0,
  "funding_stage": "Seed",
  "uses_genai": true,
  "build_patterns": [],
  "confidence_score": null,
  "tech_stack": [],
  "models_mentioned": [],
  "vertical_taxonomy": {
    "ontology_id": "startup-vertical-taxonomy",
    "ontology_version": "2026-02-07_v1",
    "primary": {
      "vertical_id": "legal",
      "vertical_label": "Legal",
      "sub_vertical_id": "compliance_monitoring",
      "sub_vertical_label": "Compliance Monitoring",
      "leaf_id": "compliance_monitoring",
      "leaf_label": "Compliance Monitoring"
    },
    "path": [
      {
        "id": "legal",
        "label": "Legal",
        "confidence": 0.8
      },
      {
        "id": "compliance_monitoring",
        "label": "Compliance Monitoring",
        "confidence": 0.85
      }
    ]
  },
  "sub_vertical": "Compliance Monitoring"
}
