{
  "company_name": "v7 Technology",
  "company_slug": "v7-technology",
  "description": "AI-powered education management platform",
  "website": "https://www.v7tech.ai",
  "location": "Istanbul, Turkey, Asia",
  "vertical": "Edutech",
  "funding_amount": 0,
  "funding_stage": null,
  "uses_genai": true,
  "build_patterns": [],
  "confidence_score": null,
  "tech_stack": [],
  "models_mentioned": [],
  "vertical_taxonomy": {
    "ontology_id": "startup-vertical-taxonomy",
    "ontology_version": "2026-02-07_v1",
    "primary": {
      "vertical_id": "education",
      "vertical_label": "Education",
      "sub_vertical_id": "education_management",
      "sub_vertical_label": "Education Management",
      "leaf_id": "education_management",
      "leaf_label": "Education Management"
    },
    "path": [
      {
        "id": "education",
        "label": "Education",
        "confidence": 1.0
      },
      {
        "id": "education_management",
        "label": "Education Management",
        "confidence": 0.95
      }
    ]
  },
  "sub_vertical": "Education Management"
}
